{
    "key": "group_59975a709d7ec",
    "title": "Resources",
    "fields": [
        {
            "key": "field_59975a7a47212",
            "label": "resource_type",
            "name": "resource_type",
            "type": "select",
            "instructions": "",
            "required": 0,
            "conditional_logic": 0,
            "wrapper": {
                "width": "",
                "class": "",
                "id": ""
            },
            "choices": {
                "Case Studies": "Case Studies",
                "White Papers": "White Papers",
                "Data Sheets": "Data Sheets",
                "Corporate Governance": "Corporate Governance",
                "Financial Reports": "Financial Reports",
                "Webinars": "Webinars"
            },
            "default_value": [
                "Case Studies"
            ],
            "allow_null": 0,
            "multiple": 0,
            "ui": 0,
            "return_format": "value",
            "ajax": 0,
            "placeholder": ""
        },
        {
            "key": "field_59975afd47213",
            "label": "resource_file_link",
            "name": "resource_file_link",
            "type": "file",
            "instructions": "",
            "required": 0,
            "conditional_logic": 0,
            "wrapper": {
                "width": "",
                "class": "",
                "id": ""
            },
            "return_format": "array",
            "library": "all",
            "min_size": "",
            "max_size": "",
            "mime_types": ""
        },
        {
            "key": "field_5d0a0fb1582c5",
            "label": "Focus Compay",
            "name": "resource_compay",
            "type": "text",
            "instructions": "",
            "required": 0,
            "conditional_logic": 0,
            "wrapper": {
                "width": "",
                "class": "",
                "id": ""
            },
            "default_value": "",
            "placeholder": "",
            "prepend": "",
            "append": "",
            "maxlength": ""
        },
        {
            "key": "field_5d0a0fc3582c6",
            "label": "Company Logo",
            "name": "company_logo",
            "type": "image",
            "instructions": "",
            "required": 0,
            "conditional_logic": 0,
            "wrapper": {
                "width": "",
                "class": "",
                "id": ""
            },
            "return_format": "array",
            "preview_size": "medium",
            "library": "all",
            "min_width": "",
            "min_height": "",
            "min_size": "",
            "max_width": "",
            "max_height": "",
            "max_size": "",
            "mime_types": ""
        },
        {
            "key": "field_5d0a0fcf582c7",
            "label": "Content",
            "name": "resource_content",
            "type": "repeater",
            "instructions": "",
            "required": 0,
            "conditional_logic": 0,
            "wrapper": {
                "width": "",
                "class": "",
                "id": ""
            },
            "collapsed": "",
            "min": 0,
            "max": 0,
            "layout": "row",
            "button_label": "",
            "sub_fields": [
                {
                    "key": "field_5d0a0fea582c8",
                    "label": "Title",
                    "name": "re_title",
                    "type": "select",
                    "instructions": "",
                    "required": 0,
                    "conditional_logic": 0,
                    "wrapper": {
                        "width": "",
                        "class": "",
                        "id": ""
                    },
                    "choices": {
                        "Industry": "Industry",
                        "The Situation": "The Situation",
                        "The Solution": "The Solution",
                        "Benefits": "Benefits",
                        "Key Success Factors": "Key Success Factors",
                        "Other": "Other"
                    },
                    "default_value": [],
                    "allow_null": 0,
                    "multiple": 0,
                    "ui": 0,
                    "return_format": "value",
                    "ajax": 0,
                    "placeholder": ""
                },
                {
                    "key": "field_5d0a100a582c9",
                    "label": "Title",
                    "name": "re_title_alt",
                    "type": "text",
                    "instructions": "",
                    "required": 0,
                    "conditional_logic": [
                        [
                            {
                                "field": "field_5d0a0fea582c8",
                                "operator": "==",
                                "value": "Other"
                            }
                        ]
                    ],
                    "wrapper": {
                        "width": "",
                        "class": "",
                        "id": ""
                    },
                    "default_value": "",
                    "placeholder": "",
                    "prepend": "",
                    "append": "",
                    "maxlength": ""
                },
                {
                    "key": "field_5d0a1033582ca",
                    "label": "Content",
                    "name": "re_content",
                    "type": "wysiwyg",
                    "instructions": "",
                    "required": 0,
                    "conditional_logic": 0,
                    "wrapper": {
                        "width": "",
                        "class": "",
                        "id": ""
                    },
                    "default_value": "",
                    "tabs": "all",
                    "toolbar": "full",
                    "media_upload": 1,
                    "delay": 0
                }
            ]
        },
        {
            "key": "field_5d0a104e582cb",
            "label": "About",
            "name": "resource_about",
            "type": "wysiwyg",
            "instructions": "",
            "required": 0,
            "conditional_logic": 0,
            "wrapper": {
                "width": "",
                "class": "",
                "id": ""
            },
            "default_value": "",
            "tabs": "all",
            "toolbar": "full",
            "media_upload": 1,
            "delay": 0
        }
    ],
    "location": [
        [
            {
                "param": "post_type",
                "operator": "==",
                "value": "resource"
            }
        ]
    ],
    "menu_order": 0,
    "position": "normal",
    "style": "default",
    "label_placement": "top",
    "instruction_placement": "label",
    "hide_on_screen": "",
    "active": 1,
    "description": "",
    "modified": 1585745538
}